gsshapyorm/__init__.py
gsshapyorm/_version.py
gsshapyorm/base/__init__.py
gsshapyorm/base/file_base.py
gsshapyorm/base/geom.py
gsshapyorm/base/rast.py
gsshapyorm/grid/land_cover/land_cover_glcf_modis.txt
gsshapyorm/grid/land_cover/land_cover_nga.txt
gsshapyorm/grid/land_cover/land_cover_nlcd.txt
gsshapyorm/lib/__init__.py
gsshapyorm/lib/check_geometry.py
gsshapyorm/lib/cif_chunk.py
gsshapyorm/lib/cmt_chunk.py
gsshapyorm/lib/db_tools.py
gsshapyorm/lib/gag_chunk.py
gsshapyorm/lib/gsshaDateTime.py
gsshapyorm/lib/parsetools.py
gsshapyorm/lib/pivot.py
gsshapyorm/lib/spn_chunk.py
gsshapyorm/lib/wms_dataset_chunk.py
gsshapyorm/orm/__init__.py
gsshapyorm/orm/cif.py
gsshapyorm/orm/cmt.py
gsshapyorm/orm/declarative_base.py
gsshapyorm/orm/ele.py
gsshapyorm/orm/evt.py
gsshapyorm/orm/file_io.py
gsshapyorm/orm/gag.py
gsshapyorm/orm/generic.py
gsshapyorm/orm/gpi.py
gsshapyorm/orm/gst.py
gsshapyorm/orm/hmet.py
gsshapyorm/orm/idx.py
gsshapyorm/orm/lnd.py
gsshapyorm/orm/loc.py
gsshapyorm/orm/map.py
gsshapyorm/orm/msk.py
gsshapyorm/orm/prj.py
gsshapyorm/orm/pro.py
gsshapyorm/orm/rep.py
gsshapyorm/orm/snw.py
gsshapyorm/orm/spn.py
gsshapyorm/orm/tim.py
gsshapyorm/orm/wms_dataset.py
gsshapyorm/util/__init__.py
gsshapyorm/util/context.py
gsshapyorm/util/log.py
gsshapyorm/util/metadata.py
gsshapyorm/util/optional.py
gsshapyorm-0.4.3.dist-info/licenses/LICENSE.txt
gsshapyorm-0.4.3.dist-info/METADATA
gsshapyorm-0.4.3.dist-info/WHEEL
gsshapyorm-0.4.3.dist-info/top_level.txt
gsshapyorm-0.4.3.dist-info/RECORD
