Metadata-Version: 2.4
Name: gsshapyorm
Version: 0.4.3
Summary: An SQLAlchemy ORM for GSSHA model files.
Author: Alan D. Snow, Scott D. Christensen
Author-email: Nathan Swain <nswain@aquaveo.com>
License: Copyright (c) 2019, Aquaveo, LLC & ERDC Computational Mechanics & Brigham Young University
Project-URL: home, https://github.com/Aquaveo/gsshapyorm
Keywords: GSSHA,database,object relational model
Classifier: Intended Audience :: Developers
Classifier: Intended Audience :: Science/Research
Classifier: Operating System :: OS Independent
Classifier: Programming Language :: Python
Classifier: Programming Language :: Python :: 3
License-File: LICENSE.txt
Requires-Dist: appdirs
Requires-Dist: geopandas
Requires-Dist: mapkit>=1.2.6
Requires-Dist: numpy
Requires-Dist: pandas
Requires-Dist: psycopg2
Requires-Dist: sqlalchemy<2
Requires-Dist: timezonefinder
Requires-Dist: pyyaml
Requires-Dist: setuptools_scm
Provides-Extra: tests
Requires-Dist: coveralls; extra == "tests"
Requires-Dist: pytest; extra == "tests"
Requires-Dist: pytest-cov; extra == "tests"
Provides-Extra: docs
Requires-Dist: mock; extra == "docs"
Requires-Dist: sphinx; extra == "docs"
Requires-Dist: sphinx_rtd_theme; extra == "docs"
Requires-Dist: sphinxcontrib-napoleon; extra == "docs"
Provides-Extra: grid
Requires-Dist: gazar; extra == "grid"
Dynamic: license-file
